inspector/__init__.py
inspector/main.py
inspector/src/__init__.py
inspector/src/parq_table.py
inspector/src/sidebar.py
inspector/src/storage_options.py
inspector/styles/basic.tcss
parq_inspector-0.2.1.dist-info/LICENSE
parq_inspector-0.2.1.dist-info/METADATA
parq_inspector-0.2.1.dist-info/WHEEL
parq_inspector-0.2.1.dist-info/entry_points.txt
parq_inspector-0.2.1.dist-info/RECORD
