Metadata-Version: 2.1
Name: parq-inspector
Version: 0.2.1
Summary: Parquet viewer for your terminal.
Home-page: https://github.com/jkausti/parq-inspector
License: MIT
Author: John Kaustinen
Author-email: jokausti@gmail.com
Requires-Python: >=3.8,<4.0
Classifier: License :: OSI Approved :: MIT License
Classifier: Programming Language :: Python :: 3
Classifier: Programming Language :: Python :: 3.8
Classifier: Programming Language :: Python :: 3.9
Classifier: Programming Language :: Python :: 3.10
Classifier: Programming Language :: Python :: 3.11
Classifier: Programming Language :: Python :: 3.12
Requires-Dist: adlfs (>=2024.2.0,<2025.0.0)
Requires-Dist: deltalake (>=0.15.0,<0.16.0)
Requires-Dist: polars (>=0.19.15,<0.20.0)
Requires-Dist: rich-click (>=1.7.1,<2.0.0)
Requires-Dist: textual (>=0.42.0,<0.43.0)
Project-URL: Repository, https://github.com/jkausti/parq-inspector
